{"id":40325,"cover":{"id":26286,"image_id":"s6nxawg4flzfsixzxylw","url":"//images.igdb.com/igdb/image/upload/t_thumb/s6nxawg4flzfsixzxylw.jpg"},"first_release_date":644198400,"genres":[{"id":14,"name":"Sport"}],"name":"Golfing Greats","release_dates":[{"id":91209,"date":644198400,"human":"Jun 01, 1990","platform":{"id":52,"name":"Arcade"},"release_region":{"id":8,"region":"worldwide"}}],"similar_games":[116353,116352,116350,116349,116351,116343,93920,114286,109606,116575],"slug":"golfing-greats","summary":"Stroke-play or match-play golfing game in a 3-D environment.","url":"https://www.igdb.com/games/golfing-greats","websites":[{"id":392911,"url":"https://www.twitch.tv/directory/game/Golfing%20Greats","type":{"id":6,"type":"Twitch"}}]}