{"id":12851,"cover":{"id":367284,"image_id":"co7vec","url":"//images.igdb.com/igdb/image/upload/t_thumb/co7vec.jpg"},"first_release_date":631065600,"genres":[{"id":4,"name":"Fighting"},{"id":8,"name":"Platform"},{"id":25,"name":"Hack and slash/Beat 'em up"}],"involved_companies":[{"id":277268,"company":{"id":881,"name":"Walking Circles"},"developer":false,"publisher":false},{"id":277269,"company":{"id":880,"name":"Domark Software"},"developer":false,"publisher":true},{"id":277267,"company":{"id":1746,"name":"Atari Games"},"developer":true,"publisher":true},{"id":277270,"company":{"id":10069,"name":"The Hit Squad"},"developer":false,"publisher":true},{"id":277271,"company":{"id":2404,"name":"Tengen"},"developer":true,"publisher":true}],"name":"Skull & Crossbones","release_dates":[{"id":620324,"date":694137600,"human":"1991","platform":{"id":15,"name":"Commodore C64/128/MAX"},"release_region":{"id":1,"region":"europe"}},{"id":620320,"date":694137600,"human":"1991","platform":{"id":16,"name":"Amiga"},"release_region":{"id":1,"region":"europe"}},{"id":620321,"date":694137600,"human":"1991","platform":{"id":25,"name":"Amstrad CPC"},"release_region":{"id":1,"region":"europe"}},{"id":620326,"date":662601600,"human":"1990","platform":{"id":18,"name":"Nintendo Entertainment System"},"release_region":{"id":2,"region":"north_america"}},{"id":620322,"date":631065600,"human":"1989","platform":{"id":52,"name":"Arcade"},"release_region":{"id":2,"region":"north_america"}},{"id":620323,"date":694137600,"human":"1991","platform":{"id":63,"name":"Atari ST/STE"},"release_region":{"id":1,"region":"europe"}},{"id":620325,"date":694137600,"human":"1991","platform":{"id":13,"name":"DOS"},"release_region":{"id":1,"region":"europe"}},{"id":620327,"date":694137600,"human":"1991","platform":{"id":26,"name":"ZX Spectrum"},"release_region":{"id":1,"region":"europe"}}],"similar_games":[54775,89550,96452,103168,101608,115283,20342,55173,24426,109277],"slug":"skull-and-crossbones","summary":"Two pirates battle against a variety of enemies while picking up treasures in a quest to find and kill The Evil Wizard.","url":"https://www.igdb.com/games/skull-and-crossbones","websites":[{"id":355246,"url":"https://www.twitch.tv/directory/game/Skull%20%26%20Crossbones","type":{"id":6,"type":"Twitch"}}]}