{"id":172649,"cover":{"id":181779,"image_id":"co3w9f","url":"//images.igdb.com/igdb/image/upload/t_thumb/co3w9f.jpg"},"first_release_date":244512000,"involved_companies":[{"id":150694,"company":{"id":817,"name":"Taito"},"developer":true,"publisher":true}],"name":"Super High-Way","release_dates":[{"id":313725,"date":244512000,"human":"Oct 1977","platform":{"id":52,"name":"Arcade"},"release_region":{"id":5,"region":"japan"}}],"slug":"super-high-way","summary":"A driving game in the style of Night Driver and 280 ZZZAP by Taito.","url":"https://www.igdb.com/games/super-high-way","websites":[{"id":470227,"url":"https://www.twitch.tv/directory/game/Super%20High-Way","type":{"id":6,"type":"Twitch"}}]}