{"id":171478,"cover":{"id":179483,"image_id":"co3uhn","url":"//images.igdb.com/igdb/image/upload/t_thumb/co3uhn.jpg"},"first_release_date":410140800,"involved_companies":[{"id":149571,"company":{"id":2523,"name":"Exidy"},"developer":true,"publisher":true}],"name":"Victor Banana","release_dates":[{"id":312119,"date":410140800,"human":"1982","platform":{"id":52,"name":"Arcade"},"release_region":{"id":2,"region":"north_america"}}],"slug":"victor-banana","url":"https://www.igdb.com/games/victor-banana","websites":[{"id":469534,"url":"https://www.twitch.tv/directory/game/Victor%20Banana","type":{"id":6,"type":"Twitch"}}]}