{"id":141238,"cover":{"id":452504,"image_id":"co9p5k","url":"//images.igdb.com/igdb/image/upload/t_thumb/co9p5k.jpg"},"genres":[{"id":8,"name":"Platform"},{"id":33,"name":"Arcade"}],"involved_companies":[{"id":316375,"company":{"id":2678,"name":"Data East"},"developer":true,"publisher":true}],"name":"Hangzo","release_dates":[{"id":219431,"human":"TBD","platform":{"id":52,"name":"Arcade"},"release_region":{"id":8,"region":"worldwide"}}],"screenshots":[{"id":409750,"image_id":"sc8s5y","url":"//images.igdb.com/igdb/image/upload/t_thumb/sc8s5y.jpg"},{"id":1509957,"image_id":"scwd39","url":"//images.igdb.com/igdb/image/upload/t_thumb/scwd39.jpg"},{"id":1509955,"image_id":"scwd37","url":"//images.igdb.com/igdb/image/upload/t_thumb/scwd37.jpg"},{"id":1509956,"image_id":"scwd38","url":"//images.igdb.com/igdb/image/upload/t_thumb/scwd38.jpg"}],"similar_games":[56033,87728,43367,96452,51485,110503,301163,260734,117311,81183],"slug":"hangzo","summary":"Hangzo is a 2D action platformer that was intended for arcades but never got released. It has since become available to play via emulation.","url":"https://www.igdb.com/games/hangzo","videos":[{"id":146483,"video_id":"Scq-DzA6Jws"}]}