{"id":5565,"alternative_names":[{"id":89525,"name":"Golden Axe: Senpuu"},{"id":89526,"name":"Golden Axe: Fighting Blades"},{"id":89527,"name":"Golden Axe Classic"}],"artworks":[{"id":77332,"image_id":"ar1no4"},{"id":77333,"image_id":"ar1no5"},{"id":77334,"image_id":"ar1no6"},{"id":261001,"image_id":"ar5le1"},{"id":261002,"image_id":"ar5le2"},{"id":261010,"image_id":"ar5lea"},{"id":261009,"image_id":"ar5le9"},{"id":261011,"image_id":"ar5leb"},{"id":261005,"image_id":"ar5le5"},{"id":261012,"image_id":"ar5lec"},{"id":261014,"image_id":"ar5lee"},{"id":261016,"image_id":"ar5leg"},{"id":261007,"image_id":"ar5le7"},{"id":261004,"image_id":"ar5le4"},{"id":261017,"image_id":"ar5leh"},{"id":261015,"image_id":"ar5lef"},{"id":261003,"image_id":"ar5le3"},{"id":261006,"image_id":"ar5le6"},{"id":261008,"image_id":"ar5le8"},{"id":261013,"image_id":"ar5led"}],"cover":{"id":100757,"image_id":"co25qt","url":"//images.igdb.com/igdb/image/upload/t_thumb/co25qt.jpg"},"first_release_date":601862400,"franchises":[{"id":1777,"name":"Golden Axe"}],"genres":[{"id":25,"name":"Hack and slash/Beat 'em up"},{"id":33,"name":"Arcade"}],"involved_companies":[{"id":56338,"company":{"id":12390,"name":"Virgin Mastertronic"},"developer":false,"publisher":true},{"id":56340,"company":{"id":617,"name":"Bandai"},"developer":false,"publisher":true},{"id":292477,"company":{"id":827,"name":"Telenet Japan"},"developer":false,"publisher":true},{"id":292478,"company":{"id":10180,"name":"Team Shinobi"},"developer":true,"publisher":false},{"id":292479,"company":{"id":33200,"name":"Renovation Game"},"developer":false,"publisher":false},{"id":377745,"company":{"id":112,"name":"Sega"},"developer":false,"publisher":true},{"id":377746,"company":{"id":7075,"name":"16 Blitz Mastertronic"},"developer":false,"publisher":true},{"id":377747,"company":{"id":10088,"name":"Dementia"},"developer":false,"publisher":false},{"id":377748,"company":{"id":1098,"name":"Probe Software"},"developer":false,"publisher":false},{"id":377749,"company":{"id":12697,"name":"Paradise Software"},"developer":false,"publisher":false},{"id":377750,"company":{"id":75127,"name":"Visual FX"},"developer":false,"publisher":false},{"id":377751,"company":{"id":4411,"name":"Tronix"},"developer":false,"publisher":true},{"id":377753,"company":{"id":21185,"name":"Backbone Emeryville"},"developer":false,"publisher":false},{"id":377755,"company":{"id":781,"name":"M2"},"developer":false,"publisher":false}],"name":"Golden Axe","rating":74.89626827593831,"rating_count":218,"release_dates":[{"id":892972,"date":662601600,"human":"1990","platform":{"id":16,"name":"Amiga"},"release_region":{"id":1,"region":"europe"}},{"id":892973,"date":662601600,"human":"1990","platform":{"id":25,"name":"Amstrad CPC"},"release_region":{"id":1,"region":"europe"}},{"id":892974,"date":601862400,"human":"Jan 27, 1989","platform":{"id":52,"name":"Arcade"},"release_region":{"id":5,"region":"japan"}},{"id":892977,"date":657417600,"human":"Nov 1990","platform":{"id":63,"name":"Atari ST/STE"},"release_region":{"id":1,"region":"europe"}},{"id":892978,"date":657417600,"human":"Nov 1990","platform":{"id":15,"name":"Commodore C64/128/MAX"},"release_region":{"id":1,"region":"europe"}},{"id":892979,"date":662601600,"human":"1990","platform":{"id":13,"name":"DOS"},"release_region":{"id":2,"region":"north_america"}},{"id":892981,"date":1311638400,"human":"Jul 26, 2011","platform":{"id":9,"name":"PlayStation 3"},"release_region":{"id":2,"region":"north_america"}},{"id":892982,"date":637545600,"human":"Mar 16, 1990","platform":{"id":150,"name":"Turbografx-16/PC Engine CD"},"release_region":{"id":5,"region":"japan"}},{"id":892983,"date":1014854400,"human":"Feb 28, 2002","platform":{"id":123,"name":"WonderSwan Color"},"release_region":{"id":5,"region":"japan"}},{"id":892984,"date":1184630400,"human":"Jul 17, 2007","platform":{"id":12,"name":"Xbox 360"},"release_region":{"id":8,"region":"worldwide"}},{"id":892985,"date":657417600,"human":"Nov 1990","platform":{"id":26,"name":"ZX Spectrum"},"release_region":{"id":1,"region":"europe"}},{"id":892975,"date":925516800,"human":"May 1999","platform":{"id":52,"name":"Arcade"},"release_region":{"id":2,"region":"north_america"}},{"id":892976,"date":925516800,"human":"May 1999","platform":{"id":52,"name":"Arcade"},"release_region":{"id":1,"region":"europe"}},{"id":892980,"date":725760000,"human":"1992","platform":{"id":13,"name":"DOS"},"release_region":{"id":1,"region":"europe"}},{"id":892986,"date":1447286400,"human":"Nov 12, 2015","platform":{"id":49,"name":"Xbox One"},"release_region":{"id":8,"region":"worldwide"}},{"id":892987,"date":1256515200,"human":"Oct 26, 2009","platform":{"id":5,"name":"Wii"},"release_region":{"id":2,"region":"north_america"}}],"screenshots":[{"id":44909,"image_id":"yqyyn9dgnylmgpjiil4s","url":"//images.igdb.com/igdb/image/upload/t_thumb/yqyyn9dgnylmgpjiil4s.jpg"},{"id":44910,"image_id":"rlpnoplh67ax6binahof","url":"//images.igdb.com/igdb/image/upload/t_thumb/rlpnoplh67ax6binahof.jpg"},{"id":160366,"image_id":"vbtuyinu58kxfdqj2vsr","url":"//images.igdb.com/igdb/image/upload/t_thumb/vbtuyinu58kxfdqj2vsr.jpg"},{"id":44907,"image_id":"v2tjomdcgg1eprriulc6","url":"//images.igdb.com/igdb/image/upload/t_thumb/v2tjomdcgg1eprriulc6.jpg"},{"id":44908,"image_id":"mywvvek5qgkoe9xdgs2t","url":"//images.igdb.com/igdb/image/upload/t_thumb/mywvvek5qgkoe9xdgs2t.jpg"},{"id":44911,"image_id":"dergbawd7l8skealeezb","url":"//images.igdb.com/igdb/image/upload/t_thumb/dergbawd7l8skealeezb.jpg"},{"id":160363,"image_id":"nkgmghn6ulyiblkyb6tw","url":"//images.igdb.com/igdb/image/upload/t_thumb/nkgmghn6ulyiblkyb6tw.jpg"},{"id":160365,"image_id":"gya8gbi8mfirfotwb6hn","url":"//images.igdb.com/igdb/image/upload/t_thumb/gya8gbi8mfirfotwb6hn.jpg"},{"id":160364,"image_id":"uvbtmlz3nrskowkk8d6k","url":"//images.igdb.com/igdb/image/upload/t_thumb/uvbtmlz3nrskowkk8d6k.jpg"},{"id":160367,"image_id":"qejuub5jiea0onyjvdu5","url":"//images.igdb.com/igdb/image/upload/t_thumb/qejuub5jiea0onyjvdu5.jpg"},{"id":160369,"image_id":"z8g59n1o1fkntlxbvcux","url":"//images.igdb.com/igdb/image/upload/t_thumb/z8g59n1o1fkntlxbvcux.jpg"},{"id":160368,"image_id":"xpmaj83ziatknqvaojqg","url":"//images.igdb.com/igdb/image/upload/t_thumb/xpmaj83ziatknqvaojqg.jpg"}],"similar_games":[5615,11646,15127,16214,16369,18182,36198,19133,9938,1652],"slug":"golden-axe","summary":"Progress is made through the game by fighting through Death Adder's henchmen, including men armed with clubs and maces, skeleton warriors, and knights. Players are able to attack using their weapon, jump and cast spells that hurt all enemies on the screen. The force of this magic depends on the number of \"bars\" of magic power currently available. The bars are filled by collecting blue 'magic potions' attained by kicking little sprites who then drop the potions. These sprites appear during regular levels and during bonus stages in between levels. The male warrior Ax is able to cast earth spells. The dwarf Gilius, casts lightning spells and the female warrior Tyris casts fire magic. Each character has a different number of maximum magic bars and varying ranges of attack.\n\nVarious steeds known as bizarrians are found in the game. These can be ridden when the enemy rider is knocked off, or if one is found dormant. The least powerful steed is known as the Cockatrice, which can be used to knock down enemies with a swipe of its tail. The more powerful dragon, which can either shoot fireballs or breathe fire, is found later in the game.","total_rating":69.94813413796916,"total_rating_count":220,"url":"https://www.igdb.com/games/golden-axe","videos":[{"id":2446,"video_id":"YB8cdGk_M3g"}],"websites":[{"id":40088,"url":"http://www.sega.com","type":{"id":1,"type":"Official Website"}},{"id":258220,"url":"https://en.wikipedia.org/wiki/Golden_Axe_(video_game)","type":{"id":3,"type":"Wikipedia"}},{"id":344472,"url":"https://www.twitch.tv/directory/game/Golden%20Axe","type":{"id":6,"type":"Twitch"}},{"id":258219,"url":"https://goldenaxe.fandom.com/wiki/Golden_Axe","type":{"id":2,"type":"Community Wiki"}}]}