{"id":20290,"alternative_names":[{"id":47232,"name":"Under Night In-Birth Exe: Late"},{"id":25223,"name":"UNIEL"},{"id":204789,"name":"UNIEL.exe"}],"artworks":[{"id":26846,"image_id":"arkpq"}],"cover":{"id":129314,"image_id":"co2rs2","url":"//images.igdb.com/igdb/image/upload/t_thumb/co2rs2.jpg"},"first_release_date":1378684800,"genres":[{"id":4,"name":"Fighting"},{"id":33,"name":"Arcade"}],"involved_companies":[{"id":37478,"company":{"id":1218,"name":"Arc System Works"},"developer":false,"publisher":true},{"id":37476,"company":{"id":6059,"name":"French Bread"},"developer":true,"publisher":false},{"id":37477,"company":{"id":6058,"name":"Ecole Software"},"developer":true,"publisher":false}],"name":"Under Night In-Birth Exe:Late","rating":70.02997273157503,"rating_count":7,"release_dates":[{"id":255230,"date":1468281600,"human":"Jul 12, 2016","platform":{"id":6,"name":"PC (Microsoft Windows)"},"release_region":{"id":2,"region":"north_america"}},{"id":343274,"date":1378684800,"human":"Sep 09, 2013","platform":{"id":52,"name":"Arcade"},"release_region":{"id":5,"region":"japan"}},{"id":106673,"date":1424995200,"human":"Feb 27, 2015","platform":{"id":9,"name":"PlayStation 3"},"release_region":{"id":1,"region":"europe"}},{"id":53617,"date":1468281600,"human":"Jul 12, 2016","platform":{"id":6,"name":"PC (Microsoft Windows)"},"release_region":{"id":8,"region":"worldwide"}},{"id":53613,"date":1406160000,"human":"Jul 24, 2014","platform":{"id":9,"name":"PlayStation 3"},"release_region":{"id":5,"region":"japan"}},{"id":106672,"date":1424736000,"human":"Feb 24, 2015","platform":{"id":9,"name":"PlayStation 3"},"release_region":{"id":2,"region":"north_america"}}],"screenshots":[{"id":27157,"image_id":"wfyyeorkrmp0vzcehawv","url":"//images.igdb.com/igdb/image/upload/t_thumb/wfyyeorkrmp0vzcehawv.jpg"},{"id":27158,"image_id":"n5zsuuohl6jswqgsqw16","url":"//images.igdb.com/igdb/image/upload/t_thumb/n5zsuuohl6jswqgsqw16.jpg"},{"id":27160,"image_id":"qs2bgawgvdcf5epywi0r","url":"//images.igdb.com/igdb/image/upload/t_thumb/qs2bgawgvdcf5epywi0r.jpg"},{"id":27161,"image_id":"jimtfxf1gpmrc0geuyxw","url":"//images.igdb.com/igdb/image/upload/t_thumb/jimtfxf1gpmrc0geuyxw.jpg"},{"id":27159,"image_id":"p0p7h9qbilfqm69bd6vu","url":"//images.igdb.com/igdb/image/upload/t_thumb/p0p7h9qbilfqm69bd6vu.jpg"}],"similar_games":[76852,57296,57372,103369,89550,36732,87728,10605,43367,96452],"slug":"under-night-in-birth-exe-late","summary":"Under Night In-Birth is a visual novel and 2D fighting game co-developed by Ecole Software and French-Bread, known for the Melty Blood series. It features a brand new cast of characters and a story that spins around modern fantasy.\n\nSega released the arcade version in Japan on September 20, 2012. A major revision of the arcade version, entitled Under Night In-Birth Exe:Late, was released on September 9, 2013. It was announced by Famitsu that Arc System Works would release the game for PlayStation 3 on July 24, 2014 in Japan. A 2015 release for North America and Europe was later announced. The North American release date, which is set for March 31, 2015, was revealed on the GameStop website. However, Aksys Games revealed the true release date for the upcoming fighter Under Night In-Birth Exe:Late, they said that the game will be releasing on February 24, 2015 for the PlayStation 3, as well as confirmed there won't be an English dub in Western releases.\n\nUnder Night In-Birth Exe:Late was released on Steam for Microsoft Windows systems on July 12, 2016.","total_rating":75.01498636578751,"total_rating_count":8,"url":"https://www.igdb.com/games/under-night-in-birth-exe-late","videos":[{"id":8887,"video_id":"H4eXXCy-e8M"}],"websites":[{"id":48820,"url":"https://store.steampowered.com/app/452510","type":{"id":13,"type":"Steam"}},{"id":48819,"url":"http://www.arcsystemworks.jp/steam/uniel/en/","type":{"id":1,"type":"Official Website"}},{"id":871618,"url":"https://inbirth.wiki.gg/wiki/UNDER_NIGHT_IN-BIRTH_Exe:Late","type":{"id":2,"type":"Community Wiki"}},{"id":112192,"url":"https://www.reddit.com/r/UnderNightInBirth","type":{"id":14,"type":"Subreddit"}},{"id":95821,"url":"https://www.facebook.com/groups/151960678810967","type":{"id":4,"type":"Facebook"}},{"id":95820,"url":"https://en.wikipedia.org/wiki/Under_Night_In-Birth","type":{"id":3,"type":"Wikipedia"}},{"id":332628,"url":"https://www.twitch.tv/directory/game/Under%20Night%20In-Birth","type":{"id":6,"type":"Twitch"}}]}