{"id":40990,"cover":{"id":26077,"image_id":"vg2a32whxte4tcoaiyrp","url":"//images.igdb.com/igdb/image/upload/t_thumb/vg2a32whxte4tcoaiyrp.jpg"},"first_release_date":410140800,"genres":[{"id":33,"name":"Arcade"}],"involved_companies":[{"id":152042,"company":{"id":1139,"name":"Cinematronics"},"developer":false,"publisher":true},{"id":152041,"company":{"id":303,"name":"Jaleco"},"developer":true,"publisher":false}],"name":"Naughty Boy","release_dates":[{"id":555308,"date":410140800,"human":"1982","platform":{"id":52,"name":"Arcade"},"release_region":{"id":2,"region":"north_america"}}],"screenshots":[{"id":1220555,"image_id":"scq5sb","url":"//images.igdb.com/igdb/image/upload/t_thumb/scq5sb.jpg"},{"id":1220556,"image_id":"scq5sc","url":"//images.igdb.com/igdb/image/upload/t_thumb/scq5sc.jpg"},{"id":1220557,"image_id":"scq5sd","url":"//images.igdb.com/igdb/image/upload/t_thumb/scq5sd.jpg"}],"similar_games":[43367,87728,112078,15851,22799,56033,113895,119207,103369,121036],"slug":"naughty-boy","summary":"You are a boy in a weird kingdom filled with even weirder monsters. Armed only with stones and your ability to aim your throws you set out to burn this place to the ground.","url":"https://www.igdb.com/games/naughty-boy","videos":[{"id":105277,"video_id":"vK8_Ygw5qrs"}],"websites":[{"id":382286,"url":"https://www.twitch.tv/directory/game/Naughty%20Boy","type":{"id":6,"type":"Twitch"}}]}