{"id":64990,"cover":{"id":129930,"image_id":"co2s96","url":"//images.igdb.com/igdb/image/upload/t_thumb/co2s96.jpg"},"first_release_date":1199059200,"genres":[{"id":31,"name":"Adventure"},{"id":33,"name":"Arcade"}],"involved_companies":[{"id":212199,"company":{"id":2255,"name":"Chillingo"},"developer":false,"publisher":true}],"name":"The Act","release_dates":[{"id":471471,"date":1199059200,"human":"2007","platform":{"id":52,"name":"Arcade"},"release_region":{"id":2,"region":"north_america"}},{"id":471472,"date":1340236800,"human":"Jun 21, 2012","platform":{"id":39,"name":"iOS"},"release_region":{"id":8,"region":"worldwide"}}],"similar_games":[56033,87622,19164,87514,81183,75242,55173,92589,58114,55190],"slug":"the-act","summary":"An interactive comedy which follows the hijinks of Edgar the window washer as he tries to woo the woman of his dreams and save his brother from a fate worse than death.","url":"https://www.igdb.com/games/the-act","videos":[{"id":149925,"video_id":"ii1UfSh7yI4"}],"websites":[{"id":372451,"url":"https://www.twitch.tv/directory/game/The%20Act","type":{"id":6,"type":"Twitch"}}]}