{"id":4511,"alternative_names":[{"id":71288,"name":"Bonanza Brothers"}],"artworks":[{"id":140651,"image_id":"ar30iz"}],"cover":{"id":289977,"image_id":"co67qx","url":"//images.igdb.com/igdb/image/upload/t_thumb/co67qx.jpg"},"first_release_date":645667200,"genres":[{"id":5,"name":"Shooter"},{"id":9,"name":"Puzzle"},{"id":33,"name":"Arcade"}],"involved_companies":[{"id":36107,"company":{"id":1453,"name":"Sharp"},"developer":false,"publisher":true},{"id":36104,"company":{"id":10073,"name":"Synergy"},"developer":true,"publisher":false},{"id":36105,"company":{"id":3668,"name":"Twilight"},"developer":true,"publisher":false},{"id":36102,"company":{"id":227,"name":"U.S. Gold"},"developer":false,"publisher":true},{"id":36101,"company":{"id":4981,"name":"Sega Enterprises, Ltd."},"developer":false,"publisher":true},{"id":36108,"company":{"id":2516,"name":"SPS"},"developer":true,"publisher":false},{"id":36103,"company":{"id":1666,"name":"Sega Europe"},"developer":false,"publisher":true},{"id":227756,"company":{"id":23993,"name":"Tec Toy"},"developer":false,"publisher":true},{"id":273465,"company":{"id":4981,"name":"Sega Enterprises, Ltd."},"developer":true,"publisher":false},{"id":273466,"company":{"id":3703,"name":"NEC"},"developer":false,"publisher":true},{"id":276376,"company":{"id":112,"name":"Sega"},"developer":false,"publisher":true}],"name":"Bonanza Bros.","rating":62.14411716843452,"rating_count":18,"release_dates":[{"id":51741,"date":694137600,"human":"1991","platform":{"id":16,"name":"Amiga"},"release_region":{"id":1,"region":"europe"}},{"id":51740,"date":694137600,"human":"1991","platform":{"id":29,"name":"Sega Mega Drive/Genesis"},"release_region":{"id":2,"region":"north_america"}},{"id":406509,"date":1284336000,"human":"Sep 13, 2010","platform":{"id":14,"name":"Mac"},"release_region":{"id":8,"region":"worldwide"}},{"id":406510,"date":1284336000,"human":"Sep 13, 2010","platform":{"id":3,"name":"Linux"},"release_region":{"id":8,"region":"worldwide"}},{"id":238936,"date":645667200,"human":"Jun 18, 1990","platform":{"id":52,"name":"Arcade"},"release_region":{"id":8,"region":"worldwide"}},{"id":456640,"date":725760000,"human":"1992","platform":{"id":26,"name":"ZX Spectrum"},"release_region":{"id":1,"region":"europe"}},{"id":437277,"date":725760000,"human":"1992","platform":{"id":64,"name":"Sega Master System/Mark III"},"release_region":{"id":10,"region":"brazil"}},{"id":505912,"date":686880000,"human":"Oct 08, 1991","platform":{"id":29,"name":"Sega Mega Drive/Genesis"},"release_region":{"id":10,"region":"brazil"}},{"id":137927,"date":1170028800,"human":"Jan 29, 2007","platform":{"id":5,"name":"Wii"},"release_region":{"id":2,"region":"north_america"}},{"id":137929,"date":1170115200,"human":"Jan 30, 2007","platform":{"id":5,"name":"Wii"},"release_region":{"id":5,"region":"japan"}},{"id":610063,"date":712540800,"human":"Jul 31, 1992","platform":{"id":150,"name":"Turbografx-16/PC Engine CD"},"release_region":{"id":5,"region":"japan"}},{"id":137928,"date":1170374400,"human":"Feb 02, 2007","platform":{"id":5,"name":"Wii"},"release_region":{"id":1,"region":"europe"}},{"id":51743,"date":694137600,"human":"1991","platform":{"id":64,"name":"Sega Master System/Mark III"},"release_region":{"id":1,"region":"europe"}},{"id":51744,"date":694137600,"human":"1991","platform":{"id":25,"name":"Amstrad CPC"},"release_region":{"id":1,"region":"europe"}},{"id":51745,"date":725760000,"human":"1992","platform":{"id":15,"name":"Commodore C64/128/MAX"},"release_region":{"id":1,"region":"europe"}},{"id":51746,"date":694137600,"human":"1991","platform":{"id":29,"name":"Sega Mega Drive/Genesis"},"release_region":{"id":1,"region":"europe"}},{"id":136933,"date":1284336000,"human":"Sep 13, 2010","platform":{"id":6,"name":"PC (Microsoft Windows)"},"release_region":{"id":8,"region":"worldwide"}}],"screenshots":[{"id":153632,"image_id":"b6zksr9meibeoxbcx2s9","url":"//images.igdb.com/igdb/image/upload/t_thumb/b6zksr9meibeoxbcx2s9.jpg"},{"id":153629,"image_id":"mlozakohecjgz2a6rerm","url":"//images.igdb.com/igdb/image/upload/t_thumb/mlozakohecjgz2a6rerm.jpg"},{"id":153633,"image_id":"llpwi9up5sggwphbonao","url":"//images.igdb.com/igdb/image/upload/t_thumb/llpwi9up5sggwphbonao.jpg"},{"id":44884,"image_id":"tmxzksofx3fupnjcfffv","url":"//images.igdb.com/igdb/image/upload/t_thumb/tmxzksofx3fupnjcfffv.jpg"},{"id":44882,"image_id":"tvcrhvarxejp1kmpwin8","url":"//images.igdb.com/igdb/image/upload/t_thumb/tvcrhvarxejp1kmpwin8.jpg"},{"id":44885,"image_id":"pixizgezvdpsfhv9st7m","url":"//images.igdb.com/igdb/image/upload/t_thumb/pixizgezvdpsfhv9st7m.jpg"},{"id":44883,"image_id":"ziok50uw7us0rzq4pyu0","url":"//images.igdb.com/igdb/image/upload/t_thumb/ziok50uw7us0rzq4pyu0.jpg"},{"id":44886,"image_id":"v4qfc7dalfovmuxkpfzq","url":"//images.igdb.com/igdb/image/upload/t_thumb/v4qfc7dalfovmuxkpfzq.jpg"},{"id":153628,"image_id":"erkqzn0dhdk5q7bhguyp","url":"//images.igdb.com/igdb/image/upload/t_thumb/erkqzn0dhdk5q7bhguyp.jpg"},{"id":153631,"image_id":"myhzca0wohmyiyqmuzap","url":"//images.igdb.com/igdb/image/upload/t_thumb/myhzca0wohmyiyqmuzap.jpg"},{"id":153630,"image_id":"sssjdab9fkmgsyxbrvcc","url":"//images.igdb.com/igdb/image/upload/t_thumb/sssjdab9fkmgsyxbrvcc.jpg"}],"similar_games":[43367,56033,18225,19164,25646,55038,110503,119177,105269,95340],"slug":"bonanza-bros","summary":"Just who are these guys?\n\nMobo and Robo are the coolest villains you'll ever meet- they rob banks, museums (and innocent computer gamers of their sanity). One evening whilst watching TV a mysterious stranger appeared on screen. \"Good Evening Boys I've got a job for you... My businesses are being robbed and I need you to test my security systems... Deliver the goods and I'll reward you.\" Take control of Mobo and Robo and guide them around the various establishments, collecting evidence on the way.","total_rating":62.14411716843452,"total_rating_count":18,"url":"https://www.igdb.com/games/bonanza-bros","websites":[{"id":69575,"url":"https://en.wikipedia.org/wiki/Bonanza_Bros.","type":{"id":3,"type":"Wikipedia"}},{"id":40075,"url":"https://store.steampowered.com/app/34284","type":{"id":13,"type":"Steam"}},{"id":69586,"url":"http://www.sega.com","type":{"id":1,"type":"Official Website"}},{"id":394149,"url":"https://www.twitch.tv/directory/game/Bonanza%20Bros.","type":{"id":6,"type":"Twitch"}}]}