{"id":317181,"alternative_names":[{"id":158305,"name":"EZ2AC : ENDLESS CIRCULATION"},{"id":158306,"name":"EZ2AC : EC"}],"cover":{"id":412268,"image_id":"co8u3w","url":"//images.igdb.com/igdb/image/upload/t_thumb/co8u3w.jpg"},"first_release_date":1367884800,"genres":[{"id":7,"name":"Music"},{"id":13,"name":"Simulator"},{"id":33,"name":"Arcade"}],"involved_companies":[{"id":287733,"company":{"id":58275,"name":"CJ Up"},"developer":false,"publisher":true},{"id":287732,"company":{"id":32345,"name":"SQUARE PIXELS"},"developer":true,"publisher":false}],"name":"EZ2AC: Endless Circulation","release_dates":[{"id":643680,"date":1367884800,"human":"May 07, 2013","platform":{"id":52,"name":"Arcade"},"release_region":{"id":9,"region":"korea"}}],"similar_games":[87150,27378,18981,112078,90965,101573,281482,183249,138548,38967],"slug":"ez2ac-endless-circulation","summary":"EZ2AC : Endless Circulation is the 11th installment of EZ2DJ/EZ2AC series. It is the first game to adopt the new EZ2AC name, retiring its old EZ2DJ name and the first game to be officially released by SQUARE PIXELS as a whole company.","url":"https://www.igdb.com/games/ez2ac-endless-circulation","videos":[{"id":126968,"video_id":"XR7Zz2UrOR0"},{"id":126969,"video_id":"tCbEpOc48lE"}],"websites":[{"id":682156,"url":"http://ez2ac.co.kr/","type":{"id":1,"type":"Official Website"}},{"id":682157,"url":"https://en.namu.wiki/w/EZ2AC%20:%20ENDLESS%20CIRCULATION","type":{"id":2,"type":"Community Wiki"}}]}