{"id":40001,"alternative_names":[{"id":9780,"name":"\u5e73\u5b89\u4eac\u30a8\u30a4\u30ea\u30a2\u30f3"}],"cover":{"id":324821,"image_id":"co6ymt","url":"//images.igdb.com/igdb/image/upload/t_thumb/co6ymt.jpg"},"first_release_date":286675200,"genres":[{"id":9,"name":"Puzzle"},{"id":15,"name":"Strategy"},{"id":32,"name":"Indie"}],"involved_companies":[{"id":75340,"company":{"id":18127,"name":"Mindware Co.,Ltd."},"developer":true,"publisher":true}],"name":"Heiankyo Alien","release_dates":[{"id":90967,"date":286675200,"human":"Feb 01, 1979","platform":{"id":52,"name":"Arcade"},"release_region":{"id":8,"region":"worldwide"}}],"screenshots":[{"id":1476911,"image_id":"scvnlb","url":"//images.igdb.com/igdb/image/upload/t_thumb/scvnlb.jpg"}],"similar_games":[36553,28070,18623,23345,30229,25311,35371,78550,14394,24426],"slug":"heiankyo-alien","summary":"The player controls a Heian period police officer who must defend the capital city from an alien invasion by digging holes in the ground and filling them back up after an alien falls inside. The player scores points for every alien trapped, and the quicker the hole is filled up after the alien falls in, the higher the number of points are scored. The aliens increase in number as the levels progress, and they can escape from holes after a certain period of time elapses or if another alien passes above their hole. The player loses if he comes in contact with an alien. There is a time limit for each level, and the number of aliens increases drastically when this limit is reached, essentially preventing the player from completing the level.","url":"https://www.igdb.com/games/heiankyo-alien","websites":[{"id":57533,"url":"https://store.steampowered.com/app/690710","type":{"id":13,"type":"Steam"}},{"id":57534,"url":"http://pinball.co.jp/games/HA/","type":{"id":1,"type":"Official Website"}},{"id":341240,"url":"https://www.twitch.tv/directory/game/Heiankyo%20Alien","type":{"id":6,"type":"Twitch"}}]}