{"id":86272,"cover":{"id":182563,"image_id":"co3wv7","url":"//images.igdb.com/igdb/image/upload/t_thumb/co3wv7.jpg"},"first_release_date":1542758400,"involved_companies":[{"id":337970,"company":{"id":9957,"name":"Byking Inc."},"developer":true,"publisher":false}],"name":"Starwing Paradox","release_dates":[{"id":788313,"date":1542758400,"human":"Nov 21, 2018","platform":{"id":52,"name":"Arcade"},"release_region":{"id":5,"region":"japan"}}],"similar_games":[89550,113895,113362,105269,306,68286,55038,100800,115283,44359],"slug":"starwing-paradox","url":"https://www.igdb.com/games/starwing-paradox","videos":[{"id":18126,"video_id":"mISUFnJ_wxQ"},{"id":18125,"video_id":"mZcPrlCk5aA"}],"websites":[{"id":391366,"url":"https://www.twitch.tv/directory/game/Starwing%20Paradox","type":{"id":6,"type":"Twitch"}},{"id":854488,"url":"https://en.wikipedia.org/wiki/Starwing_Paradox","type":{"id":3,"type":"Wikipedia"}}]}