{"id":19373,"cover":{"id":15691,"image_id":"wwwcqjlrhwmltorou5ul","url":"//images.igdb.com/igdb/image/upload/t_thumb/wwwcqjlrhwmltorou5ul.jpg"},"first_release_date":241920000,"genres":[{"id":33,"name":"Arcade"}],"involved_companies":[{"id":149386,"company":{"id":9291,"name":"RamTeK"},"developer":true,"publisher":true}],"name":"Star Cruiser","release_dates":[{"id":311856,"date":241920000,"human":"Sep 1977","platform":{"id":52,"name":"Arcade"},"release_region":{"id":2,"region":"north_america"}},{"id":121352,"date":347068800,"human":"Dec 31, 1980","platform":{"id":75,"name":"Apple II"},"release_region":{"id":2,"region":"north_america"}}],"screenshots":[{"id":24346,"image_id":"breadu7hjvjargi83tzf","url":"//images.igdb.com/igdb/image/upload/t_thumb/breadu7hjvjargi83tzf.jpg"}],"similar_games":[111846,23320,22799,55038,19249,25311,59557,105269,89550,43367],"slug":"star-cruiser","summary":"A one-on-one spaceship battle.","url":"https://www.igdb.com/games/star-cruiser"}