{"id":39907,"cover":{"id":26109,"image_id":"wwshc6kzrxzc34ofwdnb","url":"//images.igdb.com/igdb/image/upload/t_thumb/wwshc6kzrxzc34ofwdnb.jpg"},"first_release_date":770688000,"genres":[{"id":8,"name":"Platform"}],"name":"Packin Bang Bang","release_dates":[{"id":90912,"date":770688000,"human":"Jun 04, 1994","platform":{"id":52,"name":"Arcade"},"release_region":{"id":8,"region":"worldwide"}}],"similar_games":[55752,395612,393933,393128,391274,389416,388468,388305,388295,388053],"slug":"packin-bang-bang","url":"https://www.igdb.com/games/packin-bang-bang","websites":[{"id":447086,"url":"https://www.twitch.tv/directory/game/Packin%20Bang%20Bang","type":{"id":6,"type":"Twitch"}}]}