{"id":281015,"alternative_names":[{"id":178728,"name":"Earthion.exe"}],"artworks":[{"id":216379,"image_id":"ar4myj"},{"id":222276,"image_id":"ar4ric"}],"cover":{"id":477539,"image_id":"coa8gz","url":"//images.igdb.com/igdb/image/upload/t_thumb/coa8gz.jpg"},"first_release_date":1753920000,"genres":[{"id":5,"name":"Shooter"},{"id":33,"name":"Arcade"}],"involved_companies":[{"id":332307,"company":{"id":41927,"name":"exA-Arcadia"},"developer":true,"publisher":true},{"id":300608,"company":{"id":16042,"name":"Ancient Co., Ltd."},"developer":true,"publisher":false},{"id":300609,"company":{"id":31592,"name":"Limited Run Games"},"developer":false,"publisher":true}],"name":"Earthion","release_dates":[{"id":778608,"date":1753920000,"human":"Jul 31, 2025","platform":{"id":6,"name":"PC (Microsoft Windows)"},"release_region":{"id":8,"region":"worldwide"}},{"id":778612,"date":1798675200,"human":"2026","platform":{"id":29,"name":"Sega Mega Drive/Genesis"},"release_region":{"id":8,"region":"worldwide"}},{"id":779564,"date":1753920000,"human":"Jul 31, 2025","platform":{"id":52,"name":"Arcade"},"release_region":{"id":8,"region":"worldwide"}},{"id":797080,"date":1758153600,"human":"Sep 18, 2025","platform":{"id":130,"name":"Nintendo Switch"},"release_region":{"id":8,"region":"worldwide"}},{"id":840834,"date":1758153600,"human":"Sep 18, 2025","platform":{"id":48,"name":"PlayStation 4"},"release_region":{"id":8,"region":"worldwide"}},{"id":840835,"date":1758153600,"human":"Sep 18, 2025","platform":{"id":167,"name":"PlayStation 5"},"release_region":{"id":8,"region":"worldwide"}},{"id":840836,"date":1758153600,"human":"Sep 18, 2025","platform":{"id":169,"name":"Xbox Series X|S"},"release_region":{"id":8,"region":"worldwide"}},{"id":840837,"date":1758153600,"human":"Sep 18, 2025","platform":{"id":49,"name":"Xbox One"},"release_region":{"id":8,"region":"worldwide"}}],"screenshots":[{"id":1442488,"image_id":"scux14","url":"//images.igdb.com/igdb/image/upload/t_thumb/scux14.jpg"},{"id":1442485,"image_id":"scux11","url":"//images.igdb.com/igdb/image/upload/t_thumb/scux11.jpg"},{"id":1442486,"image_id":"scux12","url":"//images.igdb.com/igdb/image/upload/t_thumb/scux12.jpg"},{"id":1442487,"image_id":"scux13","url":"//images.igdb.com/igdb/image/upload/t_thumb/scux13.jpg"}],"similar_games":[22799,55038,105269,43367,68286,107318,103301,111846,113362,12539],"slug":"earthion","summary":"Earthion is an upcoming aftermarket shooting game developed by Ancient primarily for the Sega Mega Drive. Physical MD versions will be published by SUPERDELUXE GAMES in Japan and by Limited Run Games in North America. The game will also get a 16:9 version for modern platforms.\n\nEarthion is published under the label YKGGG, a brand name covering all the retro-style games developed at Ancient. If Earthion meets success, Ancient will go on the venture of releasing video games designed for retro consoles. A separate version of the game for Arcade was confirmed by Ancient and published by exA-Arcadia, which features a new, exclusive mode that will not be available in the Mega Drive version.","url":"https://www.igdb.com/games/earthion","videos":[{"id":103808,"video_id":"bxsKN-Rfvqk"},{"id":155200,"video_id":"oSdMvuhTC3o"},{"id":157670,"video_id":"KBJmYcrMx-4"}],"websites":[{"id":744296,"url":"https://earthiongame.com/","type":{"id":1,"type":"Official Website"}},{"id":751605,"url":"https://store.steampowered.com/app/3597580/Earthion/","type":{"id":13,"type":"Steam"}},{"id":864407,"url":"https://www.nintendo.com/us/store/products/earthion-switch/","type":{"id":24,"type":"Nintendo"}},{"id":872726,"url":"https://store.playstation.com/en-us/concept/10013897","type":{"id":23,"type":"Playstation"}},{"id":924572,"url":"https://www.xbox.com/en-us/games/store/earthion/9n29hbkl2zj2","type":{"id":22,"type":"Xbox"}}]}