{"id":3815,"alternative_names":[{"id":25913,"name":"Teenage Mutant Hero Turtles: The Coin Op"},{"id":92146,"name":"Super Kame Ninja"},{"id":92147,"name":"Tortues Ninja 2: Le Coin-op"},{"id":92148,"name":"Teenage Mutant Ninja Turtles: Super Kame Ninja"}],"artworks":[{"id":10526,"image_id":"ar84e"},{"id":78930,"image_id":"ar1owi"}],"cover":{"id":210345,"image_id":"co4iax","url":"//images.igdb.com/igdb/image/upload/t_thumb/co4iax.jpg"},"first_release_date":627091200,"franchises":[{"id":77,"name":"Teenage Mutant Ninja Turtles"}],"genres":[{"id":4,"name":"Fighting"},{"id":25,"name":"Hack and slash/Beat 'em up"},{"id":31,"name":"Adventure"},{"id":33,"name":"Arcade"}],"involved_companies":[{"id":175921,"company":{"id":129,"name":"Konami"},"developer":true,"publisher":true},{"id":175920,"company":{"id":888,"name":"Digital Eclipse"},"developer":false,"publisher":true},{"id":275950,"company":{"id":1098,"name":"Probe Software"},"developer":false,"publisher":false},{"id":275951,"company":{"id":4119,"name":"Mirrorsoft"},"developer":false,"publisher":true},{"id":275949,"company":{"id":1917,"name":"Image Works"},"developer":false,"publisher":false}],"name":"Teenage Mutant Ninja Turtles","rating":80.01473307977753,"rating_count":106,"release_dates":[{"id":175201,"date":662601600,"human":"1990","platform":{"id":52,"name":"Arcade"},"release_region":{"id":3,"region":"australia"}},{"id":555722,"date":1193788800,"human":"Oct 31, 2007","platform":{"id":12,"name":"Xbox 360"},"release_region":{"id":3,"region":"australia"}},{"id":175207,"date":694137600,"human":"1991","platform":{"id":15,"name":"Commodore C64/128/MAX"},"release_region":{"id":8,"region":"worldwide"}},{"id":175198,"date":627091200,"human":"Nov 15, 1989","platform":{"id":52,"name":"Arcade"},"release_region":{"id":2,"region":"north_america"}},{"id":175199,"date":631065600,"human":"1989","platform":{"id":52,"name":"Arcade"},"release_region":{"id":1,"region":"europe"}},{"id":175204,"date":694137600,"human":"1991","platform":{"id":25,"name":"Amstrad CPC"},"release_region":{"id":8,"region":"worldwide"}},{"id":175203,"date":694137600,"human":"1991","platform":{"id":16,"name":"Amiga"},"release_region":{"id":8,"region":"worldwide"}},{"id":175205,"date":694137600,"human":"1991","platform":{"id":63,"name":"Atari ST/STE"},"release_region":{"id":8,"region":"worldwide"}},{"id":555721,"date":1173830400,"human":"Mar 14, 2007","platform":{"id":12,"name":"Xbox 360"},"release_region":{"id":8,"region":"worldwide"}},{"id":175200,"date":662601600,"human":"1990","platform":{"id":52,"name":"Arcade"},"release_region":{"id":5,"region":"japan"}},{"id":175206,"date":694137600,"human":"1991","platform":{"id":13,"name":"DOS"},"release_region":{"id":8,"region":"worldwide"}}],"screenshots":[{"id":322882,"image_id":"sc6x4y","url":"//images.igdb.com/igdb/image/upload/t_thumb/sc6x4y.jpg"},{"id":322885,"image_id":"sc6x51","url":"//images.igdb.com/igdb/image/upload/t_thumb/sc6x51.jpg"},{"id":322886,"image_id":"sc6x52","url":"//images.igdb.com/igdb/image/upload/t_thumb/sc6x52.jpg"},{"id":322887,"image_id":"sc6x53","url":"//images.igdb.com/igdb/image/upload/t_thumb/sc6x53.jpg"},{"id":322888,"image_id":"sc6x54","url":"//images.igdb.com/igdb/image/upload/t_thumb/sc6x54.jpg"},{"id":322883,"image_id":"sc6x4z","url":"//images.igdb.com/igdb/image/upload/t_thumb/sc6x4z.jpg"},{"id":322890,"image_id":"sc6x56","url":"//images.igdb.com/igdb/image/upload/t_thumb/sc6x56.jpg"},{"id":322889,"image_id":"sc6x55","url":"//images.igdb.com/igdb/image/upload/t_thumb/sc6x55.jpg"}],"similar_games":[4755,4404,3817,6386,501,1376,26950,4999,9061,5181],"slug":"teenage-mutant-ninja-turtles","summary":"NOTE: This is the original 4-Player Arcade release, not the NES Title.\n\nThe player chooses from one of the four Ninja Turtles: Leonardo, Michelangelo, Donatello, and Raphael. After Shredder kidnaps the Turtles' friend April O'Neil and their mentor Splinter, they must give chase, save their comrades, and defeat the evil Shredder.\n\nThe player chooses from one of the four Ninja Turtles: Leonardo, Michelangelo, Donatello, and Raphael. Depending on the version of the game, the characters are either, chosen at the start of the game or assigned by control panel. After Shredder kidnaps the Turtles' friend April O'Neil and their mentor Splinter, they must give chase, save their comrades, and defeat the evil Shredder. Up to four players (two in some versions) can take control of any of the Turtles. Donatello has slower attacks but a longer range, Michelangelo and Raphael have faster attacks but a shorter range, and Leonardo is a well-rounded Turtle with average range and speed.\n\nThe eight-way joystick controls the movements of the Turtle, the jump button makes them jump and the attack button makes them hit in front of them using their weapon. In addition to this, some combinations are possible. The Turtles can throw Foot soldiers overhead, and by pressing the jump and attack buttons, a special attack is performed. Raphael rolls along the ground and finishes with a kick, while the other Turtles do a sweeping jump attack with their weapons. Turtles can also spring off the wall in certain areas. Enemies can be defeated more quickly by slamming them into walls or solid objects. Many objects such as traffic cones, parking meters, fire hydrants and exploding oil drums can be hit or damaged with attacks in order to help defeat nearby enemies. In the attract mode, the game showed the first part of the cartoon opening, along with a portion of the Teenage Mutant Ninja Turtles theme song.\n\nMost of the enemies the Turtles face are the Foot Soldiers, all color-coded to indicate their attack patterns and weapon of choices. Some enemies, such as the standard purple-clad Foot Soldiers and Roadkill Rodney robots, have the ability to restrain the Turtles' mobility and drain their health, leaving the player open to attack for other enemies. The bosses in the game include Rocksteady and Bebop (individually at first in that order, and later the two of them together), Baxter Stockman, Granitor, General Traag, Krang, and Shredder himself.","total_rating":62.50736653988876,"total_rating_count":108,"url":"https://www.igdb.com/games/teenage-mutant-ninja-turtles","videos":[{"id":29782,"video_id":"_0kKGOQOYxg"}],"websites":[{"id":145750,"url":"https://arcade1up.com/products/teenage-mutant-ninja-turtles","type":{"id":1,"type":"Official Website"}},{"id":145752,"url":"https://twitter.com/TMNT","type":{"id":5,"type":"Twitter"}},{"id":145751,"url":"https://www.facebook.com/teenagemutantninjaturtles","type":{"id":4,"type":"Facebook"}},{"id":114360,"url":"https://en.wikipedia.org/wiki/Teenage_Mutant_Ninja_Turtles_(arcade_game)","type":{"id":3,"type":"Wikipedia"}},{"id":114359,"url":"https://turtlepedia.fandom.com/wiki/Teenage_Mutant_Ninja_Turtles_(arcade_game)","type":{"id":2,"type":"Community Wiki"}}]}