{"id":154828,"alternative_names":[{"id":127920,"name":"GITADORA Matixx"}],"cover":{"id":157534,"image_id":"co3djy","url":"//images.igdb.com/igdb/image/upload/t_thumb/co3djy.jpg"},"first_release_date":1504656000,"franchises":[{"id":1651,"name":"Bemani"},{"id":2880,"name":"GuitarFreaks"}],"genres":[{"id":7,"name":"Music"},{"id":33,"name":"Arcade"}],"involved_companies":[{"id":141308,"company":{"id":22806,"name":"Konami Amusement"},"developer":true,"publisher":true}],"name":"Gitadora Matixx","release_dates":[{"id":297480,"date":1504656000,"human":"Sep 06, 2017","platform":{"id":52,"name":"Arcade"},"release_region":{"id":5,"region":"japan"}}],"screenshots":[{"id":513799,"image_id":"scb0g7","url":"//images.igdb.com/igdb/image/upload/t_thumb/scb0g7.jpg"},{"id":513800,"image_id":"scb0g8","url":"//images.igdb.com/igdb/image/upload/t_thumb/scb0g8.jpg"}],"similar_games":[18981,87150,63933,77720,82995,78969,80106,90965,322338,154836],"slug":"gitadora-matixx","summary":"The fifth game in the Gitadora series, a spinoff series of the GituarFreaks and DrumMania franchises.","url":"https://www.igdb.com/games/gitadora-matixx","videos":[{"id":51965,"video_id":"COnO5HYkwyQ"}],"websites":[{"id":196800,"url":"https://ja.wikipedia.org/wiki/GITADORA","type":{"id":3,"type":"Wikipedia"}},{"id":196797,"url":"https://web.archive.org/web/20190331040622/https://p.eagate.573.jp/game/gfdm/gitadora_matixx/p/index.html","type":{"id":1,"type":"Official Website"}},{"id":196798,"url":"https://twitter.com/gfdm_staff","type":{"id":5,"type":"Twitter"}},{"id":196799,"url":"https://bemaniwiki.com/index.php?GITADORA%20Matixx","type":{"id":2,"type":"Community Wiki"}},{"id":461217,"url":"https://www.twitch.tv/directory/game/GITADORA%20Matixx","type":{"id":6,"type":"Twitch"}}]}