{"id":111304,"alternative_names":[{"id":123944,"name":"RECORDBREAKER"}],"cover":{"id":299068,"image_id":"co6erg","url":"//images.igdb.com/igdb/image/upload/t_thumb/co6erg.jpg"},"first_release_date":599529600,"genres":[{"id":13,"name":"Simulator"},{"id":14,"name":"Sport"}],"involved_companies":[{"id":238486,"company":{"id":817,"name":"Taito"},"developer":true,"publisher":true}],"name":"Recordbreaker","release_dates":[{"id":398731,"date":599529600,"human":"1988","platform":{"id":52,"name":"Arcade"},"release_region":{"id":8,"region":"worldwide"}}],"screenshots":[{"id":258115,"image_id":"sc5j5v","url":"//images.igdb.com/igdb/image/upload/t_thumb/sc5j5v.jpg"},{"id":258114,"image_id":"sc5j5u","url":"//images.igdb.com/igdb/image/upload/t_thumb/sc5j5u.jpg"},{"id":907295,"image_id":"scjg2n","url":"//images.igdb.com/igdb/image/upload/t_thumb/scjg2n.jpg"},{"id":907296,"image_id":"scjg2o","url":"//images.igdb.com/igdb/image/upload/t_thumb/scjg2o.jpg"}],"similar_games":[116353,115869,112846,118871,116667,114285,106814,120126,103218,102805],"slug":"recordbreaker","summary":"Recordbreaker is a multi-event sports game for one or two players, where the player tries to achieve a world-record score in each of ten competitions. The events include: 100m sprint, 4x100m relay, Triple jump, Pole vault, Long horse, 100m swimming, Weightlifting, Horizontal bar, 100m hurdles and Shot put. The events can be played in any order, although losing an event results in the end of the game.","url":"https://www.igdb.com/games/recordbreaker","websites":[{"id":436769,"url":"https://www.twitch.tv/directory/game/RECORDBREAKER","type":{"id":6,"type":"Twitch"}}]}