{"id":69888,"cover":{"id":443574,"image_id":"co9i9i","url":"//images.igdb.com/igdb/image/upload/t_thumb/co9i9i.jpg"},"first_release_date":1072828800,"genres":[{"id":33,"name":"Arcade"}],"involved_companies":[{"id":290274,"company":{"id":817,"name":"Taito"},"developer":true,"publisher":true}],"name":"Space Invaders Anniversary","release_dates":[{"id":245982,"date":1072828800,"human":"2003","platform":{"id":8,"name":"PlayStation 2"},"release_region":{"id":8,"region":"worldwide"}},{"id":245983,"date":1072828800,"human":"2003","platform":{"id":52,"name":"Arcade"},"release_region":{"id":8,"region":"worldwide"}},{"id":245984,"date":1072828800,"human":"2003","platform":{"id":6,"name":"PC (Microsoft Windows)"},"release_region":{"id":8,"region":"worldwide"}}],"similar_games":[73905,22290,42761,111846,39725,39769,22799,4614,77488,72305],"slug":"space-invaders-anniversary","summary":"Space Invaders Anniversary celebrates the 25th anniversary of the oldest Taito franchise.","url":"https://www.igdb.com/games/space-invaders-anniversary","websites":[{"id":359943,"url":"https://www.twitch.tv/directory/game/Space%20Invaders%20Anniversary","type":{"id":6,"type":"Twitch"}}]}