{"id":66967,"alternative_names":[{"id":67766,"name":"Too Spicy"}],"cover":{"id":258274,"image_id":"co5jaa","url":"//images.igdb.com/igdb/image/upload/t_thumb/co5jaa.jpg"},"first_release_date":1177459200,"genres":[{"id":4,"name":"Fighting"},{"id":5,"name":"Shooter"}],"involved_companies":[{"id":191119,"company":{"id":112,"name":"Sega"},"developer":false,"publisher":true},{"id":191120,"company":{"id":6002,"name":"SEGA AM1"},"developer":true,"publisher":false}],"name":"2 Spicy","release_dates":[{"id":397236,"date":1177459200,"human":"Apr 25, 2007","platform":{"id":52,"name":"Arcade"},"release_region":{"id":8,"region":"worldwide"}}],"screenshots":[{"id":904966,"image_id":"scje9y","url":"//images.igdb.com/igdb/image/upload/t_thumb/scje9y.jpg"},{"id":904968,"image_id":"scjea0","url":"//images.igdb.com/igdb/image/upload/t_thumb/scjea0.jpg"},{"id":904967,"image_id":"scje9z","url":"//images.igdb.com/igdb/image/upload/t_thumb/scje9z.jpg"},{"id":904969,"image_id":"scjea1","url":"//images.igdb.com/igdb/image/upload/t_thumb/scjea1.jpg"}],"similar_games":[95340,89550,119177,38030,106805,87622,32902,43367,28751,105269],"slug":"2-spicy","summary":"2 Spicy (or Too Spicy) is a light-gun shooter arcade game developed by Sega. It uses a unique foot controller in addition to a standard light gun. It has both a two-player multiplayer and a story mode with cinematics.","url":"https://www.igdb.com/games/2-spicy","videos":[{"id":76500,"video_id":"UBsyQzOewUM"}],"websites":[{"id":366918,"url":"https://www.twitch.tv/directory/game/2%20Spicy","type":{"id":6,"type":"Twitch"}}]}