{"id":123084,"cover":{"id":338705,"image_id":"co79ch","url":"//images.igdb.com/igdb/image/upload/t_thumb/co79ch.jpg"},"first_release_date":220838400,"genres":[{"id":4,"name":"Fighting"}],"involved_companies":[{"id":235416,"company":{"id":16725,"name":"Project Support Engineering"},"developer":true,"publisher":true}],"name":"Knights in Armor","release_dates":[{"id":528299,"date":220838400,"human":"1976","platform":{"id":52,"name":"Arcade"},"release_region":{"id":2,"region":"north_america"}}],"slug":"knights-in-armor","summary":"A jousting match between knights.","url":"https://www.igdb.com/games/knights-in-armor","videos":[{"id":100042,"video_id":"lEF9w-ArQc4"}],"websites":[{"id":388837,"url":"https://www.twitch.tv/directory/game/Knights%20in%20Armor","type":{"id":6,"type":"Twitch"}}]}