{"id":39659,"alternative_names":[{"id":110564,"name":"\u30c9\u30e9\u30b4\u30f3\u30d6\u30ec\u30a4\u30ba for Nintendo Switch"},{"id":103578,"name":"\ub4dc\ub798\uace4 \ube14\ub808\uc774\uc988"},{"id":103554,"name":"\ub4dc\ub798\uace4 \ube14\ub808\uc774\uc988(Dragon Blaze)"},{"id":191489,"name":"dragonblaze.exe"}],"artworks":[{"id":51840,"image_id":"ar1400"}],"cover":{"id":124309,"image_id":"co2nx1","url":"//images.igdb.com/igdb/image/upload/t_thumb/co2nx1.jpg"},"first_release_date":949363200,"genres":[{"id":5,"name":"Shooter"},{"id":12,"name":"Role-playing (RPG)"},{"id":13,"name":"Simulator"},{"id":15,"name":"Strategy"},{"id":16,"name":"Turn-based strategy (TBS)"},{"id":33,"name":"Arcade"}],"involved_companies":[{"id":168427,"company":{"id":2888,"name":"Psikyo"},"developer":true,"publisher":true}],"name":"Dragon Blaze","rating":77.73409695371203,"rating_count":6,"release_dates":[{"id":327320,"date":1522886400,"human":"Apr 05, 2018","platform":{"id":130,"name":"Nintendo Switch"},"release_region":{"id":5,"region":"japan"}},{"id":150378,"date":1151020800,"human":"Jun 23, 2006","platform":{"id":8,"name":"PlayStation 2"},"release_region":{"id":1,"region":"europe"}},{"id":226691,"date":1596412800,"human":"Aug 03, 2020","platform":{"id":6,"name":"PC (Microsoft Windows)"},"release_region":{"id":8,"region":"worldwide"}},{"id":437200,"date":1673395200,"human":"Jan 11, 2023","platform":{"id":49,"name":"Xbox One"},"release_region":{"id":2,"region":"north_america"}},{"id":446735,"date":1522886400,"human":"Apr 05, 2018","platform":{"id":130,"name":"Nintendo Switch"},"release_region":{"id":8,"region":"worldwide"}},{"id":93581,"date":949363200,"human":"Feb 01, 2000","platform":{"id":52,"name":"Arcade"},"release_region":{"id":8,"region":"worldwide"}}],"screenshots":[{"id":210847,"image_id":"uagxwendgyjbhrkdgwza","url":"//images.igdb.com/igdb/image/upload/t_thumb/uagxwendgyjbhrkdgwza.jpg"},{"id":210849,"image_id":"dphb3zqecu0xvpsvkdky","url":"//images.igdb.com/igdb/image/upload/t_thumb/dphb3zqecu0xvpsvkdky.jpg"},{"id":210848,"image_id":"pf1zlezzzrlddxifczui","url":"//images.igdb.com/igdb/image/upload/t_thumb/pf1zlezzzrlddxifczui.jpg"},{"id":210846,"image_id":"aztazt9fbxri0xrwejfe","url":"//images.igdb.com/igdb/image/upload/t_thumb/aztazt9fbxri0xrwejfe.jpg"},{"id":210845,"image_id":"wiilndqlzkswpf6zeep8","url":"//images.igdb.com/igdb/image/upload/t_thumb/wiilndqlzkswpf6zeep8.jpg"},{"id":210850,"image_id":"qyuutg0mriukc3efd9ea","url":"//images.igdb.com/igdb/image/upload/t_thumb/qyuutg0mriukc3efd9ea.jpg"}],"similar_games":[25311,35994,28182,26574,8422,95340,103232,58075,13196,36553],"slug":"dragon-blaze","summary":"Dragon Blaze is a vertical scrolling shoot 'em up arcade game released in 2000 by Psikyo. It was ported in 2004 to the PlayStation 2 as part of the Psikyo Shooting Collection Vol. 3:Sol Divide & Dragon Blaze compilation. The game was later also released on its own for the PS2 in Europe by 505 Games.","total_rating":76.86704847685601,"total_rating_count":7,"url":"https://www.igdb.com/games/dragon-blaze","websites":[{"id":895702,"url":"https://psikyo-portal.com/","type":{"id":1,"type":"Official Website"}},{"id":759970,"url":"https://www.nintendo.com/store/products/dragon-blaze-for-nintendo-switch-switch/","type":{"id":24,"type":"Nintendo"}},{"id":759972,"url":"https://store.playstation.com/en-us/concept/10001928","type":{"id":23,"type":"Playstation"}},{"id":167827,"url":"https://store.steampowered.com/app/1279420","type":{"id":13,"type":"Steam"}},{"id":343584,"url":"https://www.twitch.tv/directory/game/Dragon%20Blaze","type":{"id":6,"type":"Twitch"}}]}