{"id":281570,"alternative_names":[{"id":154900,"name":"ONGEKI bright MEMORY"},{"id":168969,"name":"\u30aa\u30f3\u30b2\u30ad bright MEMORY"},{"id":168966,"name":"O.N.G.E.K.I. bright MEMORY"}],"artworks":[{"id":142461,"image_id":"ar31x9"}],"cover":{"id":353788,"image_id":"co7kzg","url":"//images.igdb.com/igdb/image/upload/t_thumb/co7kzg.jpg"},"first_release_date":1646265600,"genres":[{"id":7,"name":"Music"},{"id":33,"name":"Arcade"}],"involved_companies":[{"id":246562,"company":{"id":112,"name":"Sega"},"developer":true,"publisher":true}],"name":"Ongeki Bright Memory","release_dates":[{"id":622547,"date":1646265600,"human":"Mar 03, 2022","platform":{"id":52,"name":"Arcade"},"release_region":{"id":5,"region":"japan"}}],"similar_games":[77720,87150,18981,78969,76901,174357,90965,393672,325313,315977],"slug":"ongeki-bright-memory","summary":"Ongeki Bright Memory introduced the \"Memories of O.N.G.E.K.I\" event, allowing players to unlock songs and items by completing specific chapter challenges. All songs from this event were made publicly available to all players in 2024.","url":"https://www.igdb.com/games/ongeki-bright-memory","videos":[{"id":120783,"video_id":"L8dcClLlSy4"}],"websites":[{"id":658037,"url":"https://twitter.com/ongeki_official","type":{"id":5,"type":"Twitter"}},{"id":719827,"url":"https://silentblue.remywiki.com/ONGEKI:bright_MEMORY","type":{"id":2,"type":"Community Wiki"}},{"id":605388,"url":"https://ongeki.sega.jp/","type":{"id":1,"type":"Official Website"}},{"id":658036,"url":"https://www.youtube.com/c/ONGEKI","type":{"id":9,"type":"YouTube"}}]}