{"id":1564,"alternative_names":[{"id":152260,"name":"\u7075\u9b42\u80fd\u529b"},{"id":152261,"name":"SC"},{"id":152262,"name":"Soul Calibur"}],"artworks":[{"id":47851,"image_id":"ar10x7"}],"cover":{"id":89656,"image_id":"co1x6g","url":"//images.igdb.com/igdb/image/upload/t_thumb/co1x6g.jpg"},"first_release_date":901756800,"franchises":[{"id":2005,"name":"SoulCalibur"}],"genres":[{"id":4,"name":"Fighting"},{"id":33,"name":"Arcade"}],"involved_companies":[{"id":19207,"company":{"id":263,"name":"Namco"},"developer":false,"publisher":true},{"id":19206,"company":{"id":732,"name":"Project Soul"},"developer":true,"publisher":false},{"id":99597,"company":{"id":6330,"name":"Namco Bandai Games"},"developer":false,"publisher":false}],"name":"SoulCalibur","rating":83.80829590015098,"rating_count":126,"release_dates":[{"id":596548,"date":1384905600,"human":"Nov 20, 2013","platform":{"id":34,"name":"Android"},"release_region":{"id":8,"region":"worldwide"}},{"id":22185,"date":901756800,"human":"Jul 30, 1998","platform":{"id":52,"name":"Arcade"},"release_region":{"id":5,"region":"japan"}},{"id":22190,"date":944006400,"human":"Dec 01, 1999","platform":{"id":23,"name":"Dreamcast"},"release_region":{"id":1,"region":"europe"}},{"id":231448,"date":1214956800,"human":"Jul 02, 2008","platform":{"id":12,"name":"Xbox 360"},"release_region":{"id":8,"region":"worldwide"}},{"id":22186,"date":915062400,"human":"1998","platform":{"id":52,"name":"Arcade"},"release_region":{"id":2,"region":"north_america"}},{"id":22188,"date":933811200,"human":"Aug 05, 1999","platform":{"id":23,"name":"Dreamcast"},"release_region":{"id":5,"region":"japan"}},{"id":596549,"date":1326931200,"human":"Jan 19, 2012","platform":{"id":39,"name":"iOS"},"release_region":{"id":8,"region":"worldwide"}},{"id":22187,"date":915062400,"human":"1998","platform":{"id":52,"name":"Arcade"},"release_region":{"id":1,"region":"europe"}},{"id":22189,"date":936835200,"human":"Sep 09, 1999","platform":{"id":23,"name":"Dreamcast"},"release_region":{"id":2,"region":"north_america"}}],"screenshots":[{"id":41084,"image_id":"s9ipzmiq7u64aycojdtr","url":"//images.igdb.com/igdb/image/upload/t_thumb/s9ipzmiq7u64aycojdtr.jpg"},{"id":41085,"image_id":"ris8pkzuaq6rvztesdsk","url":"//images.igdb.com/igdb/image/upload/t_thumb/ris8pkzuaq6rvztesdsk.jpg"},{"id":41087,"image_id":"vwkz3e1s7ymmg6bldmtp","url":"//images.igdb.com/igdb/image/upload/t_thumb/vwkz3e1s7ymmg6bldmtp.jpg"},{"id":7262,"image_id":"szehhawj6k5lv2sqnrnj","url":"//images.igdb.com/igdb/image/upload/t_thumb/szehhawj6k5lv2sqnrnj.jpg"},{"id":41086,"image_id":"vv1hrmvymllwlztdv92y","url":"//images.igdb.com/igdb/image/upload/t_thumb/vv1hrmvymllwlztdv92y.jpg"}],"similar_games":[1244,1245,1563,1565,1566,1243,1242,7331,1249,1567],"slug":"soulcalibur","summary":"SoulCalibur is a weapon-based 3D fighting game developed by Project Soul and produced by Namco. It is the second game in the Soul series, preceded by Soul Edge (1996). Originally released in arcades in 1998, it ran on the Namco System 12 hardware. In 1999 it was ported to the Dreamcast with improved graphics and new features. The North American version was released in September 1999 as a launch title for the Dreamcast and was part of the successful launch of the new console. It became available as a downloadable title on Xbox 360's Xbox Live Marketplace in 2008.\nThe title brought many innovations to the fighting game genre that include a heavy emphasis on weapons and a unique eight-way movement system. Soulcalibur is widely regarded as one of the best Dreamcast titles and is one of the most critically acclaimed fighting games of all time.","total_rating":71.9041479500755,"total_rating_count":128,"url":"https://www.igdb.com/games/soulcalibur","videos":[{"id":3094,"video_id":"iXDL0lm8diQ"}],"websites":[{"id":638666,"url":"https://play.google.com/store/apps/details?id=com.namcobandaigames.soulcaliburgp","type":{"id":12,"type":"Google Play"}},{"id":141272,"url":"https://twitter.com/soulcalibur","type":{"id":5,"type":"Twitter"}},{"id":19930,"url":"http://www.soulcalibur.com/","type":{"id":1,"type":"Official Website"}},{"id":19931,"url":"http://soulcalibur.wikia.com/wiki/Soulcalibur","type":{"id":2,"type":"Community Wiki"}},{"id":334517,"url":"https://www.twitch.tv/directory/game/Soulcalibur","type":{"id":6,"type":"Twitch"}},{"id":638667,"url":"https://apps.apple.com/fr/app/soulcalibur/id481958471","type":{"id":10,"type":"App Store (iPhone)"}},{"id":141271,"url":"https://en.wikipedia.org/wiki/Soulcalibur_(video_game)","type":{"id":3,"type":"Wikipedia"}}]}